odoo8_addon_medical_family-8.0.1.1.0.99.dev4-py2.7-nspkg.pth
odoo8_addon_medical_family-8.0.1.1.0.99.dev4.dist-info/DESCRIPTION.rst
odoo8_addon_medical_family-8.0.1.1.0.99.dev4.dist-info/METADATA
odoo8_addon_medical_family-8.0.1.1.0.99.dev4.dist-info/RECORD
odoo8_addon_medical_family-8.0.1.1.0.99.dev4.dist-info/WHEEL
odoo8_addon_medical_family-8.0.1.1.0.99.dev4.dist-info/metadata.json
odoo8_addon_medical_family-8.0.1.1.0.99.dev4.dist-info/namespace_packages.txt
odoo8_addon_medical_family-8.0.1.1.0.99.dev4.dist-info/top_level.txt
odoo_addons/medical_family/README.rst
odoo_addons/medical_family/__init__.py
odoo_addons/medical_family/__openerp__.py
odoo_addons/medical_family/i18n/pt_BR.po
odoo_addons/medical_family/i18n/sl.po
odoo_addons/medical_family/models/__init__.py
odoo_addons/medical_family/models/medical_family.py
odoo_addons/medical_family/models/medical_family_role.py
odoo_addons/medical_family/models/medical_patient.py
odoo_addons/medical_family/security/ir.model.access.csv
odoo_addons/medical_family/views/medical_family_view.xml
odoo_addons/medical_family/views/medical_patient_view.xml
